Selection_Fair/Selection_Fair.py
Selection_Fair/__init__.py
selection_fair-0.0.1.dist-info/METADATA
selection_fair-0.0.1.dist-info/WHEEL
selection_fair-0.0.1.dist-info/top_level.txt
selection_fair-0.0.1.dist-info/RECORD
