Metadata-Version: 2.4
Name: Selection_Fair
Version: 0.0.1
Summary: 表格数据处理器，用于处理销售数据并生成选货排位等信息
Author: DongYang
Author-email: 649898871@qq.com
License: MIT
Classifier: Programming Language :: Python :: 3
Classifier: Programming Language :: Python :: 3.7
Classifier: Programming Language :: Python :: 3.8
Classifier: Programming Language :: Python :: 3.9
Classifier: Operating System :: Microsoft :: Windows
Classifier: Intended Audience :: Developers
Classifier: Topic :: Software Development :: Libraries :: Python Modules
Requires-Python: >=3.7
Requires-Dist: pandas>=1.3.0
